Metadata-Version: 2.1
Name: odoo-addon-l10n_es_pos
Version: 16.0.1.0.3
Summary: Punto de venta adaptado a la legislación española
Home-page: https://github.com/OCA/l10n-spain
Author: Tecnativa, Aselcis Consulting, Acysos S.L., Odoo Community Association (OCA)
Author-email: support@odoo-community.org
License: AGPL-3
Classifier: Programming Language :: Python
Classifier: Framework :: Odoo
Classifier: Framework :: Odoo :: 16.0
Classifier: License :: OSI Approved :: GNU Affero General Public License v3
Requires-Python: >=3.10
Requires-Dist: odoo<16.1dev,>=16.0a
